satiopst/__init__.py
satiopst/extracttraindata.py
satiopst/filters.py
satiopst/imageFrame.py
satiopst/imgReadWrite.py
satiopst/transfrom.py
satiopst/ts_convR.py
satiopst/utils.py
SatIOpsT-0.0.9.dist-info/LICENSE.txt
SatIOpsT-0.0.9.dist-info/METADATA
SatIOpsT-0.0.9.dist-info/WHEEL
SatIOpsT-0.0.9.dist-info/top_level.txt
SatIOpsT-0.0.9.dist-info/RECORD
