Metadata-Version: 2.1
Name: SatIOpsT
Version: 0.0.9
Summary: Satellite Image Operations Toolbox
Home-page: https://github.com/SubhadipDatta/SatIOpsT/wiki
Author: GeoEspacioTech Pvt. Ltd., Subhadip Datta, Soumyadeep Dutta
Author-email: geoespaciotech@gmail.com
License: MIT
Platform: UNKNOWN
Classifier: Programming Language :: Python :: 3
Classifier: License :: OSI Approved :: MIT License
Classifier: Operating System :: OS Independent
Requires-Dist: geopandas
Requires-Dist: rasterio
Requires-Dist: scipy
Requires-Dist: pandas
Requires-Dist: numpy
